compas_nurbs/__init__.py
compas_nurbs/__version__.py
compas_nurbs/bspline.py
compas_nurbs/conftest.py
compas_nurbs/curvature.py
compas_nurbs/curve.py
compas_nurbs/evaluators.py
compas_nurbs/fitting.py
compas_nurbs/helpers.py
compas_nurbs/knot_vectors.py
compas_nurbs/operations.py
compas_nurbs/surface.py
compas_nurbs/utilities.py
compas_nurbs/data/bsplines_data.json
compas_nurbs/data/cylinder.json
compas_nurbs/data/surface.json
compas_nurbs/ghpython/__init__.py
compas_nurbs/ghpython/curve_artist.py
compas_nurbs/ghpython/geometry.py
compas_nurbs/ghpython/surface_artist.py
compas_nurbs/rhino/__init__.py
compas_nurbs/rhino/curve_artist.py
compas_nurbs/rhino/install.py
compas_nurbs/rhino/surface_artist.py
compas_nurbs-0.2.0.dist-info/AUTHORS.rst
compas_nurbs-0.2.0.dist-info/LICENSE
compas_nurbs-0.2.0.dist-info/METADATA
compas_nurbs-0.2.0.dist-info/WHEEL
compas_nurbs-0.2.0.dist-info/top_level.txt
compas_nurbs-0.2.0.dist-info/RECORD
