Metadata-Version: 2.1
Name: compas-nurbs
Version: 0.2.0
Summary: NURBS for COMPAS
Home-page: https://github.com/gramaziokohler/compas_nurbs
Author: Gramazio Kohler Research
Author-email: gramaziokohler@arch.ethz.ch
License: MIT license
Keywords: compas,nurbs,rhino,bspline
Platform: UNKNOWN
Classifier: Development Status :: 3 - Alpha
Classifier: Intended Audience :: Developers
Classifier: Intended Audience :: Science/Research
Classifier: License :: OSI Approved :: MIT License
Classifier: Operating System :: Unix
Classifier: Operating System :: POSIX
Classifier: Operating System :: Microsoft :: Windows
Classifier: Programming Language :: Python
Classifier: Programming Language :: Python :: 3
Classifier: Programming Language :: Python :: 3.4
Classifier: Programming Language :: Python :: 3.5
Classifier: Programming Language :: Python :: 3.6
Classifier: Programming Language :: Python :: 3.7
Classifier: Programming Language :: Python :: 3.8
Classifier: Programming Language :: Python :: Implementation :: CPython
Classifier: Topic :: Scientific/Engineering
Requires-Dist: compas (<2.0,>=1.0)
